py_apollo/__init__.py
py_apollo/apollo_client.py
py_apollo-0.0.3.dist-info/LICENSE
py_apollo-0.0.3.dist-info/METADATA
py_apollo-0.0.3.dist-info/WHEEL
py_apollo-0.0.3.dist-info/top_level.txt
py_apollo-0.0.3.dist-info/RECORD
