Metadata-Version: 2.1
Name: py-apollo
Version: 0.0.3
Summary: pyapollo from filamoon
Home-page: https://github.com/filamoon/pyapollo
Author: filamoon
Author-email: filamoon@gmail.com
License: UNKNOWN
Platform: any
Classifier: Programming Language :: Python
Classifier: Programming Language :: Python :: 2.7
Requires-Dist: requests
